perso_lib/__init__.py
perso_lib/algorithm.py
perso_lib/apdu.py
perso_lib/chip_config.py
perso_lib/cps.py
perso_lib/cps_perso.py
perso_lib/excel.py
perso_lib/file_handle.py
perso_lib/gen_kmc_session.py
perso_lib/ini_parse.py
perso_lib/kms.py
perso_lib/log.py
perso_lib/mock_dp.py
perso_lib/pcsc.py
perso_lib/perso_log_parse.py
perso_lib/rule.py
perso_lib/settings.py
perso_lib/smart_qc.py
perso_lib/utils.py
perso_lib/word.py
perso_lib/xml_parse.py
perso_lib/dll/Authencation.dll
perso_lib/dll/ChineseSM.dll
perso_lib/dll/DataParse.dll
perso_lib/dll/DataParse_bak.dll
perso_lib/dll/Des0.dll
perso_lib/dll/Log.dll
perso_lib/dll/PCSC.dll
perso_lib/dll/Tool.dll
perso_lib/dll/libeay32.dll
perso_lib/dll/sqlite3.dll
perso_lib/dp_format/__init__.py
perso_lib/dp_format/ge_dp.py
perso_lib/dp_format/goldpac_dp.py
perso_lib/dp_format/ht_dp.py
perso_lib/dp_format/ht_tong_lian_dp.py
perso_lib/dp_format/jy_xml_dp.py
perso_lib/dp_format/szsm_dp.py
perso_lib/dp_format/yinlian_dp.py
perso_lib/dp_format/zx_dp.py
perso_lib/template/DpRequirement.docx
perso_lib/template/jetco/JETCO_Common_Template1_PT.xml
perso_lib/template/mc/MCA_Common_PT.xml
perso_lib/template/uics/UICS_Common_PT.xml
perso_lib/template/visa/VAP4CF_PT.xml
perso_lib/template/visa/VAP4C_PT.xml
perso_lib/template/visa/VAP4DF_PT.xml
perso_lib/template/visa/VAP4D_PT.xml
perso_lib/template/visa/VCD_PT.xml
perso_lib/template/visa/V_D_CommonF_PT.xml
perso_lib/transaction/__init__.py
perso_lib/transaction/trans_base.py
perso_lib/transaction/trans_mc.py
perso_lib/transaction/trans_pse.py
perso_lib/transaction/trans_pure.py
perso_lib/transaction/trans_visa.py
perso_lib/transaction/cases/__init__.py
perso_lib/transaction/cases/helper.py
perso_lib/transaction/cases/base/__init__.py
perso_lib/transaction/cases/base/case_application_selection.py
perso_lib/transaction/cases/base/case_get_data.py
perso_lib/transaction/cases/base/case_gpo.py
perso_lib/transaction/cases/base/case_read_record.py
perso_lib/transaction/cases/jetco/__init__.py
perso_lib-2.0.0.11.dist-info/METADATA
perso_lib-2.0.0.11.dist-info/WHEEL
perso_lib-2.0.0.11.dist-info/top_level.txt
perso_lib-2.0.0.11.dist-info/RECORD
