Metadata-Version: 2.1
Name: perso-lib
Version: 2.0.0.11
Summary: A lib for parse dp data
Home-page: https://github.com/z-zroud/CardScript
Author: z_road
Author-email: 489469935@qq.com
License: UNKNOWN
Platform: UNKNOWN
Classifier: Programming Language :: Python :: 3
Classifier: License :: OSI Approved :: MIT License
Classifier: Operating System :: OS Independent
Requires-Dist: openpyxl
Requires-Dist: python-docx
Requires-Dist: pillow
Requires-Dist: six
Requires-Dist: colorama
